dlibex/__init__.py
dlibex/module.py
dlibex-1.12.dist-info/METADATA
dlibex-1.12.dist-info/WHEEL
dlibex-1.12.dist-info/top_level.txt
dlibex-1.12.dist-info/RECORD
