Metadata-Version: 2.1
Name: dlibex
Version: 1.12
Summary: This library is used for malware development. For educational purposes only!
Home-page: 
Author: Anthony
Author-email: anthonyadams9821@gmail.com
Classifier: Programming Language :: Python :: 3
Classifier: License :: OSI Approved :: MIT License
Classifier: Operating System :: OS Independent
Requires-Python: >=3.6
Requires-Dist: requests
